remmina_password_exposer/remmina_password_exposer.py
remmina_password_exposer/__init__.py
remmina_password_exposer-0.3.dist-info/RECORD
remmina_password_exposer-0.3.dist-info/DESCRIPTION.rst
remmina_password_exposer-0.3.dist-info/METADATA
remmina_password_exposer-0.3.dist-info/top_level.txt
remmina_password_exposer-0.3.dist-info/metadata.json
remmina_password_exposer-0.3.dist-info/WHEEL
remmina_password_exposer-0.3.data/scripts/remmina_password_exposer.py
