Metadata-Version: 2.0
Name: remmina-password-exposer
Version: 0.3
Summary: Print remmina password in clear
Home-page: https://github.com/peppelinux/Remmina-password-exposer
Author: Giuseppe De Marco
Author-email: giuseppe.demarco@unical.it
License: BSD
Platform: UNKNOWN
Classifier: Development Status :: 5 - Production/Stable
Classifier: License :: OSI Approved :: BSD License
Classifier: Programming Language :: Python :: 2
Classifier: Programming Language :: Python :: 3
Requires-Dist: pycrypto
